LICENSE
README.md
setup.py
easystac/__init__.py
easystac/base.py
easystac/logging_utils.py
easystac.egg-info/PKG-INFO
easystac.egg-info/SOURCES.txt
easystac.egg-info/dependency_links.txt
easystac.egg-info/requires.txt
easystac.egg-info/top_level.txt
easystac/planetary/__init__.py
easystac/planetary/image_collection.py
easystac/radiant/__init__.py
easystac/radiant/image_collection.py