Metadata-Version: 2.1
Name: easystac
Version: 0.0.1
Summary: A Python package for simple STAC queries
Home-page: https://github.com/cloudsen12/easystac
Author: David Montero Loaiza and Cesar Aybar Camacho
Author-email: dml.mont@gmail.com
License: MIT
Platform: UNKNOWN
Classifier: Development Status :: 2 - Pre-Alpha
Classifier: License :: OSI Approved :: MIT License
Classifier: Programming Language :: Python :: 3.7
Classifier: Programming Language :: Python :: 3.8
Classifier: Programming Language :: Python :: 3.9
License-File: LICENSE
